quark_plugin_salbp/__init__.py
quark_plugin_salbp/salbp_instance.py
quark_plugin_salbp/salbp_instance_provider.py
quark_plugin_salbp/salbp_mip_mapping.py
quark_plugin_salbp/data/example_instance_n=10.alb
quark_plugin_salbp/data/example_instance_n=20.alb
quark_plugin_salbp/data/example_instance_n=3.alb
quark_plugin_salbp/data/example_instance_n=5.alb
quark_plugin_salbp-0.1.1.dist-info/licenses/LICENSE
quark_plugin_salbp-0.1.1.dist-info/licenses/NOTICE
quark_plugin_salbp-0.1.1.dist-info/METADATA
quark_plugin_salbp-0.1.1.dist-info/WHEEL
quark_plugin_salbp-0.1.1.dist-info/top_level.txt
quark_plugin_salbp-0.1.1.dist-info/RECORD
